Metadata-Version: 2.1
Name: django-heroku-memcacheify
Version: 1.0.1
Summary: Automatic Django memcached configuration on Heroku.
Home-page: https://github.com/rdegges/django-heroku-memcacheify
Author: Randall Degges
Author-email: r@rdegges.com
License: UNLICENSE
Keywords: django heroku cloud cache memcache memcached awesome epic
Platform: UNKNOWN
Classifier: Framework :: Django
Classifier: Programming Language :: Python :: 2
Classifier: Programming Language :: Python :: 2.7
Classifier: Programming Language :: Python :: 3
Classifier: Programming Language :: Python :: 3.5
